cdk_apisix/__init__.py
cdk_apisix/py.typed
cdk_apisix/_jsii/__init__.py
cdk_apisix/_jsii/cdk-apisix@0.0.303.jsii.tgz
cdk_apisix-0.0.303.dist-info/LICENSE
cdk_apisix-0.0.303.dist-info/METADATA
cdk_apisix-0.0.303.dist-info/WHEEL
cdk_apisix-0.0.303.dist-info/top_level.txt
cdk_apisix-0.0.303.dist-info/RECORD
